<?xml version="1.0" encoding="utf-8"?>

<configuration>
    <PBinaries>D:\git\p\bld\Drops\debug\x64\Binaries</PBinaries>
    <PSTools>D:\tools\pstools</PSTools>
    <MainExe>D:\git\P\Bld\Drops\Debug\x86\Samples\PingPong\PingPong.exe</MainExe>
    <NodeManagerPort>5600</NodeManagerPort>
    <ContainerPortStart>5900</ContainerPortStart>
    <NetworkShare>.\DebugLocal\</NetworkShare>
    <LocalFolder>.\DebugLocal\</LocalFolder>
    <MainMachineNode>localhost</MainMachineNode>
    <CentralServer>localhost</CentralServer>
    <TotalNodes>1</TotalNodes>
    <AllNodes>
        <Node>localhost</Node>
    </AllNodes>
</configuration>
